LICENSE
MANIFEST.in
README.md
setup.py
py_dela.egg-info/PKG-INFO
py_dela.egg-info/SOURCES.txt
py_dela.egg-info/dependency_links.txt
py_dela.egg-info/top_level.txt
pydela/__init__.py
pydela/lexicon.py